{"dish":[{"id":1,"name":"Margherita Pizza","category":"Pizza","price":9.99,"isAvailable":true,"description":"Classic pizza with tomato, mozzarella, and fresh basil."},{"id":2,"name":"Chicken Biryani","category":"Rice","price":11.49,"isAvailable":true,"description":"Fragrant basmati rice cooked with marinated chicken and spices."}],"dishes":[{"id":1,"name":"Margherita Pizza","category":"Pizza","price":9.99,"isAvailable":true,"description":"Classic pizza with tomato, mozzarella, and fresh basil."},{"id":2,"name":"Chicken Biryani","category":"Rice","price":15,"isAvailable":true,"description":"Fragrant basmati rice cooked with marinated chicken and spices."}]}